spandas/__init__.py
spandas-0.0.1.dist-info/METADATA
spandas-0.0.1.dist-info/RECORD
spandas-0.0.1.dist-info/WHEEL
spandas-0.0.1.dist-info/top_level.txt
